README.md
setup.py
repotool/__init__.py
repotool/__main__.py
repotool/bitbucket.py
repotool/github.py
repotool/gitlab.py
repotool/owner.py
repotool/project.py
repotool/table.py
repotool.egg-info/PKG-INFO
repotool.egg-info/SOURCES.txt
repotool.egg-info/dependency_links.txt
repotool.egg-info/entry_points.txt
repotool.egg-info/not-zip-safe
repotool.egg-info/requires.txt
repotool.egg-info/top_level.txt