Metadata-Version: 1.1
Name: repotool
Version: 0.3
Summary: Python wrappers around GitHub, GitLab and Bitbucket REST APIs
Home-page: https://github.com/rcook/repotool
Author: Richard Cook
Author-email: rcook@rcook.org
License: MIT
Platform: UNKNOWN
Classifier: Development Status :: 3 - Alpha
Classifier: License :: OSI Approved :: MIT License
Classifier: Programming Language :: Python :: 2.7
